README.rst
setup.py
concurapi/__init__.py
concurapi/client.py
concurapi/exceptions.py
concurapi/test_client.py
concurapi.egg-info/PKG-INFO
concurapi.egg-info/SOURCES.txt
concurapi.egg-info/dependency_links.txt
concurapi.egg-info/top_level.txt
concurapi/models/__init__.py
concurapi/models/objects.py
concurapi/models/resource.py
concurapi/models/test_users.py
concurapi/models/users.py